mapie/__init__.py
mapie/_machine_precision.py
mapie/_version.py
mapie/aggregation_functions.py
mapie/calibration.py
mapie/classification.py
mapie/subsample.py
mapie/utils.py
mapie/conformity_scores/__init__.py
mapie/conformity_scores/classification.py
mapie/conformity_scores/interface.py
mapie/conformity_scores/regression.py
mapie/conformity_scores/utils.py
mapie/conformity_scores/bounds/__init__.py
mapie/conformity_scores/bounds/absolute.py
mapie/conformity_scores/bounds/gamma.py
mapie/conformity_scores/bounds/residuals.py
mapie/conformity_scores/sets/__init__.py
mapie/conformity_scores/sets/aps.py
mapie/conformity_scores/sets/lac.py
mapie/conformity_scores/sets/naive.py
mapie/conformity_scores/sets/raps.py
mapie/conformity_scores/sets/topk.py
mapie/conformity_scores/sets/utils.py
mapie/estimator/__init__.py
mapie/estimator/classifier.py
mapie/estimator/regressor.py
mapie/metrics/__init__.py
mapie/metrics/calibration.py
mapie/metrics/classification.py
mapie/metrics/regression.py
mapie/regression/__init__.py
mapie/regression/quantile_regression.py
mapie/regression/regression.py
mapie/regression/time_series_regression.py
mapie/risk_control/__init__.py
mapie/risk_control/binary_classification.py
mapie/risk_control/methods.py
mapie/risk_control/multi_label_classification.py
mapie/risk_control/risks.py
mapie/tests/__init__.py
mapie/tests/test_aggregations_functions.py
mapie/tests/test_calibration.py
mapie/tests/test_classification.py
mapie/tests/test_common.py
mapie/tests/test_conformity_scores_bounds.py
mapie/tests/test_conformity_scores_sets.py
mapie/tests/test_conformity_scores_utils.py
mapie/tests/test_metrics.py
mapie/tests/test_non_regression.py
mapie/tests/test_quantile_regression.py
mapie/tests/test_regression.py
mapie/tests/test_subsample.py
mapie/tests/test_time_series_regression.py
mapie/tests/test_utils.py
mapie/tests/long_tests/test_theoretical_validity.py
mapie/tests/risk_control/test_binary_classification_control.py
mapie-1.2.1.dist-info/licenses/LICENSE
mapie-1.2.1.dist-info/METADATA
mapie-1.2.1.dist-info/WHEEL
mapie-1.2.1.dist-info/top_level.txt
mapie-1.2.1.dist-info/RECORD
