Metadata-Version: 2.4
Name: MAPIE
Version: 1.2.1
Summary: A scikit-learn-compatible module for estimating prediction intervals.
Maintainer-email: Valentin Laurent <valentin.laurent@capgemini.com>, Louis Lacombe <louis.lacombe@capgemini.com>, Vincent Blot <vincent.blot@capgemini.com>, Geoffray Brelurut <geoffray.brelurut@capgemini.com>, Hassan Maissoro <hassan.maissoro@capgemini.com>, Adrien Le Coz <adrien.le-coz@inria.fr>
License-Expression: BSD-3-Clause
Project-URL: Homepage, https://github.com/scikit-learn-contrib/MAPIE
Project-URL: Documentation, https://mapie.readthedocs.io/en/latest/
Project-URL: Repository, https://github.com/scikit-learn-contrib/MAPIE
Project-URL: Issues, https://github.com/scikit-learn-contrib/MAPIE/issues
Project-URL: Changelog, https://github.com/scikit-learn-contrib/MAPIE/releases
Project-URL: DOWNLOAD, https://pypi.org/project/MAPIE/#files
Classifier: Intended Audience :: Science/Research
Classifier: Intended Audience :: Developers
Classifier: Topic :: Software Development
Classifier: Topic :: Scientific/Engineering
Classifier: Operating System :: Microsoft :: Windows
Classifier: Operating System :: POSIX
Classifier: Operating System :: Unix
Classifier: Operating System :: MacOS
Classifier: Programming Language :: Python :: 3.9
Classifier: Programming Language :: Python :: 3.10
Classifier: Programming Language :: Python :: 3.11
Classifier: Programming Language :: Python :: 3.12
Classifier: Programming Language :: Python :: 3.13
Requires-Python: >=3.9
License-File: LICENSE
Requires-Dist: numpy<2.4,>=1.24.1
Requires-Dist: scikit-learn<1.8,>=1.4
Requires-Dist: scipy>=1.10
Provides-Extra: dev
Requires-Dist: bump2version==1.0.1; extra == "dev"
Requires-Dist: build==1.3.0; extra == "dev"
Requires-Dist: codecov==2.1.13; extra == "dev"
Requires-Dist: mypy<1.15; extra == "dev"
Requires-Dist: pandas==2.3.3; extra == "dev"
Requires-Dist: pytest==8.4.2; extra == "dev"
Requires-Dist: pytest-cov==7.0.0; extra == "dev"
Requires-Dist: ruff==0.14.3; extra == "dev"
Requires-Dist: twine==6.2.0; extra == "dev"
Requires-Dist: wheel==0.45.1; extra == "dev"
Provides-Extra: docs
Requires-Dist: lightgbm==4.4.0; extra == "docs"
Requires-Dist: matplotlib==3.9.4; extra == "docs"
Requires-Dist: numpydoc==1.9.0; extra == "docs"
Requires-Dist: pandas==2.3.3; extra == "docs"
Requires-Dist: sphinx==7.4.7; extra == "docs"
Requires-Dist: sphinx-gallery==0.19.0; extra == "docs"
Requires-Dist: sphinx_rtd_theme==3.0.2; extra == "docs"
Requires-Dist: typing_extensions==4.0.1; extra == "docs"
Provides-Extra: notebooks
Requires-Dist: ipykernel==6.31.0; extra == "notebooks"
Requires-Dist: jupyter==1.1.1; extra == "notebooks"
Requires-Dist: jupyterlab==4.4.10; extra == "notebooks"
Requires-Dist: jupytext==1.18.1; extra == "notebooks"
Requires-Dist: matplotlib==3.9.4; extra == "notebooks"
Requires-Dist: nbconvert==7.16.6; extra == "notebooks"
Requires-Dist: pandas==2.3.3; extra == "notebooks"
Requires-Dist: scikeras==0.13.0; extra == "notebooks"
Requires-Dist: seaborn==0.13.2; extra == "notebooks"
Requires-Dist: tensorflow==2.20.0; extra == "notebooks"
Requires-Dist: tensorflow_datasets==4.8.3; extra == "notebooks"
Requires-Dist: xgboost==2.1.4; extra == "notebooks"
Dynamic: license-file
